frf/__init__.py
frf/app.py
frf/settings.py
frf/core/RepositoryBase.py
frf/core/__init__.py
frf/database/ModelBase.py
frf/database/__init__.py
frf/database/db_engine.py
frf/depends/__init__.py
frf/depends/database.py
frf/mixins/FrfBase.py
frf/mixins/GetViewMixin.py
frf/mixins/__init__.py
frf/schemas/__init__.py
sireleot_frf-0.1.0.dist-info/METADATA
sireleot_frf-0.1.0.dist-info/WHEEL
sireleot_frf-0.1.0.dist-info/top_level.txt
sireleot_frf-0.1.0.dist-info/RECORD
